email_controller/__init__.py
email_controller/base_configurations.py
email_controller/contact_handler.py
email_controller/record_validation.py
email_controller/response_handler.py
email_controller/smtp_controller.py
unittests/__init__.py
unittests/test_email_controller.py
unittests/test_response_handler.py
email_controller-0.0.14.dist-info/LICENSE
email_controller-0.0.14.dist-info/METADATA
email_controller-0.0.14.dist-info/WHEEL
email_controller-0.0.14.dist-info/top_level.txt
email_controller-0.0.14.dist-info/RECORD
