Metadata-Version: 2.1
Name: email-controller
Version: 0.0.14
Summary: Package for just basic SMTP email sending
Home-page: https://github.com/jamberin/email_controller
Author: James Beringer
Author-email: jamberin@gmail.com
License: UNKNOWN
Platform: UNKNOWN
Classifier: Programming Language :: Python :: 3.7
Classifier: Development Status :: 2 - Pre-Alpha
Classifier: License :: Public Domain
